<?xml version="1.0" encoding="UTF-8"?>
<feature
      id="com.iar.cdt.arm.debugger.feature"
      label="IAR C-SPY Debug Support for ARM"
      version="6.50.2.201401141319"
      provider-name="IAR Systems AB">

   <description url="http://www.iar.com">
      IAR debugger integration for ARM.
   </description>

   <copyright>
      Copyright 2013 IAR Systems AB
   </copyright>

   <requires>
      <import feature="com.iar.cdt.arm.sdk.feature" version="6.50.0.qualifier"/>
      <import feature="org.eclipse.emf.databinding" version="1.2.0.v20100914-1218"/>
      <import feature="com.iar.common.debugger.feature" version="1.0.0.qualifier"/>
      <import feature="com.iar.common.feature" version="1.0.0.qualifier"/>
   </requires>

   <plugin
         id="com.iar.cdt.arm.debugger"
         download-size="35"
         install-size="75"
         version="1.1.1.201401141319"
         unpack="false"/>

   <plugin
         id="com.iar.cdt.arm.debugger.jlink"
         download-size="90"
         install-size="190"
         version="1.4.0.201401141319"
         unpack="false"/>

   <plugin
         id="com.iar.cdt.arm.debugger.sim"
         download-size="15"
         install-size="35"
         version="0.9.0.201401141319"
         unpack="false"/>

   <plugin
         id="com.iar.ide.debugger.rtos.cmx"
         download-size="14"
         install-size="32"
         version="0.9.0.201401141319"
         unpack="false"/>

   <plugin
         id="com.iar.cdt.arm.debugger.ijet"
         download-size="128"
         install-size="282"
         version="0.13.3.201401141319"
         unpack="false"/>

   <plugin
         id="com.iar.ide.debugger.driver.arm"
         download-size="139"
         install-size="370"
         version="1.0.0.201401141319"
         unpack="false"/>

   <plugin
         id="com.iar.ide.debugger.driver.arm.ui"
         download-size="128"
         install-size="261"
         version="1.0.0.201401141319"
         unpack="false"/>

   <plugin
         id="com.iar.ide.debugger.driver.armdriverlib"
         download-size="42"
         install-size="99"
         version="1.0.0.201401141319"
         unpack="false"/>

   <plugin
         id="com.iar.ide.debugger.driver.armdriverlib.ui"
         download-size="14"
         install-size="25"
         version="1.0.0.201401141319"
         unpack="false"/>

   <plugin
         id="com.iar.ide.debugger.driver.ijet"
         download-size="86"
         install-size="270"
         version="1.0.0.201401141319"
         unpack="false"/>

   <plugin
         id="com.iar.ide.debugger.driver.ijet.ui"
         download-size="103"
         install-size="202"
         version="1.0.0.201401141319"
         unpack="false"/>

</feature>
